eazytv/__init__.py
eazytv/__version__.py
eazytv/cli.py
eazytv/utils.py
eazytv/data/shows.csv
eazytv/eztv/__init__.py
eazytv/eztv/database.py
eazytv/eztv/eztv.py
eazytv/eztv/parser.py
eazytv-0.3.1.dist-info/METADATA
eazytv-0.3.1.dist-info/RECORD
eazytv-0.3.1.dist-info/WHEEL
eazytv-0.3.1.dist-info/entry_points.txt
eazytv-0.3.1.dist-info/top_level.txt
